bebe_task_recorder/__init__.py
bebe_task_recorder/bebe_gui.py
bebe_task_recorder-1.0.1.dist-info/licenses/LICENSE
bebe_task_recorder-1.0.1.dist-info/METADATA
bebe_task_recorder-1.0.1.dist-info/WHEEL
bebe_task_recorder-1.0.1.dist-info/entry_points.txt
bebe_task_recorder-1.0.1.dist-info/top_level.txt
bebe_task_recorder-1.0.1.dist-info/RECORD
